
    {
    "game": {
             
                "LZ5T4R4YX6CZEFLBE6PO2UWHZCM":
                 {
                  "type": "spin_wheel",
                  "scoring_type":"proportional",

                  
                   "levels": [
                   
                    {
                     "id":"LMDRHISLUJOVUFIVFY7KSMAKSXQ",
                    "level_id": 0,
                    "level_name": "Easy",
                    "scoring_system": {
                        "max_score": 10,
                        "partial_score": 8,
                        "partial_score_2": 5
                             },
                    "items": [
                    
                        {
                            "item_id": 0,
                            "item_type": "question",
                            "item_icon": "",
                            
                                "data": {
                                        "component_name": "question",
                                        "component_id": "LOAFZX2ELNWYUJCVOB237NIQ2R4",
                                        "file_name": [ "question", "question_7H42UVS3MALULLR23NS63FN25Q"]
                                    }
                                     
                        } 
                            ]
                     } ,
                    {
                     "id":"LWZTS6V7EO56EHALDXS23JC72FI",
                    "level_id": 1,
                    "level_name": "Medium",
                    "scoring_system": {
                        "max_score": 10,
                        "partial_score": 8,
                        "partial_score_2": 5
                             },
                    "items": [
                    
                        {
                            "item_id": 0,
                            "item_type": "question",
                            "item_icon": "",
                            
                                "data": {
                                        "component_name": "question",
                                        "component_id": "LX235AECJGK4ERPM7OWJWIV7PAE",
                                        "file_name": [ "question", "question_7H42UVS3MALULLR23NS63FN25Q"]
                                    }
                                     
                        } 
                            ]
                     } ,
                    {
                     "id":"LEAA2FOS3DLDETB6PY3CO7WSSCU",
                    "level_id": 2,
                    "level_name": "Hard",
                    "scoring_system": {
                        "max_score": 10,
                        "partial_score": 8,
                        "partial_score_2": 5
                             },
                    "items": [
                    
                        {
                            "item_id": 0,
                            "item_type": "question",
                            "item_icon": "",
                            
                                "data": {
                                        "component_name": "question",
                                        "component_id": "LOKYNC6ZYDNDU7EABBRLZNZE2HE",
                                        "file_name": [ "question", "question_7H42UVS3MALULLR23NS63FN25Q"]
                                    }
                                     
                        } 
                            ]
                     } 
              ]
                 
                  }
                ,
                "LKXWLUP3YACWEDKXD6EJX7KGPII":
                 {
                  "type": "popping_matter",
                  "scoring_type":"proportional",

                  
                   "levels": [
                   
                    {
                     "id":"LKBQ5Y2ISYXXUDC7LKAYLCKBU2U",
                    "level_id": 0,
                    "level_name": "Easy",
                    "scoring_system": {
                        "max_score": 10,
                        "partial_score": 8,
                        "partial_score_2": 5
                             },
                    "items": [
                    
                        {
                            "item_id": 0,
                            "item_type": "question",
                            "item_icon": "",
                            
                                "data": {
                                        "component_name": "question",
                                        "component_id": "LJ4KDIIEQJWAEXE66TRVN3N467U",
                                        "file_name": [ "question", "question_7H42UVS3MALULLR23NS63FN25Q"]
                                    }
                                     
                        } 
                            ]
                     } ,
                    {
                     "id":"L5JHSB4KIDB4EJKJ2OTGJSYHU3Q",
                    "level_id": 1,
                    "level_name": "Medium",
                    "scoring_system": {
                        "max_score": 10,
                        "partial_score": 8,
                        "partial_score_2": 5
                             },
                    "items": [
                    
                        {
                            "item_id": 0,
                            "item_type": "question",
                            "item_icon": "",
                            
                                "data": {
                                        "component_name": "question",
                                        "component_id": "L5XZIDS4VHBJEPFUOX6NQXW62PQ",
                                        "file_name": [ "question", "question_7H42UVS3MALULLR23NS63FN25Q"]
                                    }
                                     
                        } 
                            ]
                     } ,
                    {
                     "id":"LTRNTWNLPO4IEVIVM7DVRY3MLD4",
                    "level_id": 2,
                    "level_name": "Hard",
                    "scoring_system": {
                        "max_score": 10,
                        "partial_score": 8,
                        "partial_score_2": 5
                             },
                    "items": [
                    
                        {
                            "item_id": 0,
                            "item_type": "question",
                            "item_icon": "",
                            
                                "data": {
                                        "component_name": "question",
                                        "component_id": "LYWAM4N6B7CDUFM2HSCAWQBP234",
                                        "file_name": [ "question", "question_7H42UVS3MALULLR23NS63FN25Q"]
                                    }
                                     
                        } 
                            ]
                     } 
              ]
                 
                  }
                ,
                "L6NVE7LK5RK5UZIBKLICASTS6RI":
                 {
                  "type": "planet",
                  "scoring_type":"proportional",

                  
                   "levels": [
                   
                    {
                     "id":"LJRTMSXCNO5MUTHJJC2DNRILJCE",
                    "level_id": 0,
                    "level_name": "Easy",
                    "scoring_system": {
                        "max_score": 10,
                        "partial_score": 8,
                        "partial_score_2": 5
                             },
                    "items": [
                    
                        {
                            "item_id": 0,
                            "item_type": "question",
                            "item_icon": "",
                            
                                "data": {
                                        "component_name": "question",
                                        "component_id": "LT3KJRJER2LDEXFIMELMP2LCVKI",
                                        "file_name": [ "question", "question_7H42UVS3MALULLR23NS63FN25Q"]
                                    }
                                     
                        } 
                            ]
                     } ,
                    {
                     "id":"LNQZCSLR33NKE5OJ325BHWYLQ5E",
                    "level_id": 1,
                    "level_name": "Medium",
                    "scoring_system": {
                        "max_score": 10,
                        "partial_score": 8,
                        "partial_score_2": 5
                             },
                    "items": [
                    
                        {
                            "item_id": 0,
                            "item_type": "question",
                            "item_icon": "",
                            
                                "data": {
                                        "component_name": "question",
                                        "component_id": "LSDDWTAOUNQ3EPHMYJOX5KZWI3E",
                                        "file_name": [ "question", "question_7H42UVS3MALULLR23NS63FN25Q"]
                                    }
                                     
                        } 
                            ]
                     } ,
                    {
                     "id":"LCRYZP7G2LINEJMI5XL6M4GTK44",
                    "level_id": 2,
                    "level_name": "Hard",
                    "scoring_system": {
                        "max_score": 10,
                        "partial_score": 8,
                        "partial_score_2": 5
                             },
                    "items": [
                    
                        {
                            "item_id": 0,
                            "item_type": "question",
                            "item_icon": "",
                            
                                "data": {
                                        "component_name": "question",
                                        "component_id": "LBNUJ4Y42PPAE5LDYSEMJ4LRD3E",
                                        "file_name": [ "question", "question_7H42UVS3MALULLR23NS63FN25Q"]
                                    }
                                     
                        } 
                            ]
                     } 
              ]
                 
                  }
                ,
                "LJPBIDD7FPJRU7JHCDN4ZNEZZSI":
                 {
                  "type": "balloon",
                  "scoring_type":"proportional",

                  
                   "levels": [
                   
                    {
                     "id":"LGNR67ZYWTQPE5L2SHFJWZV4FBU",
                    "level_id": 0,
                    "level_name": "Easy",
                    "scoring_system": {
                        "max_score": 10,
                        "partial_score": 8,
                        "partial_score_2": 5
                             },
                    "items": [
                    
                        {
                            "item_id": 0,
                            "item_type": "question",
                            "item_icon": "",
                            
                                "data": {
                                        "component_name": "question",
                                        "component_id": "L6EUI5KHLCNRUPNJF7SU4FSYAME",
                                        "file_name": [ "question", "question_7H42UVS3MALULLR23NS63FN25Q"]
                                    }
                                     
                        } 
                            ]
                     } ,
                    {
                     "id":"LYDVYQHX7KNUU7OAYJAIJVB3SYA",
                    "level_id": 1,
                    "level_name": "Medium",
                    "scoring_system": {
                        "max_score": 10,
                        "partial_score": 8,
                        "partial_score_2": 5
                             },
                    "items": [
                    
                        {
                            "item_id": 0,
                            "item_type": "question",
                            "item_icon": "",
                            
                                "data": {
                                        "component_name": "question",
                                        "component_id": "LV22JSGYIMAEUXNQAKUPJBWDAIU",
                                        "file_name": [ "question", "question_7H42UVS3MALULLR23NS63FN25Q"]
                                    }
                                     
                        } 
                            ]
                     } ,
                    {
                     "id":"LFOBYPXBTC2RUROKCOIBISEN3UU",
                    "level_id": 2,
                    "level_name": "Hard",
                    "scoring_system": {
                        "max_score": 10,
                        "partial_score": 8,
                        "partial_score_2": 5
                             },
                    "items": [
                    
                        {
                            "item_id": 0,
                            "item_type": "question",
                            "item_icon": "",
                            
                                "data": {
                                        "component_name": "question",
                                        "component_id": "LLKWVP5SWQNKULG6YVYPFBFZHAI",
                                        "file_name": [ "question", "question_7H42UVS3MALULLR23NS63FN25Q"]
                                    }
                                     
                        } 
                            ]
                     } 
              ]
                 
                  }
                ,
                "LFCF6YOJD2HGE3BIRSKOIP7HLXQ":
                 {
                  "type": "basketball",
                  "scoring_type":"proportional",

                  
                   "levels": [
                   
                    {
                     "id":"L7RJ3POHCXC2E7A7YCUMAWCT6VM",
                    "level_id": 0,
                    "level_name": "Easy",
                    "scoring_system": {
                        "max_score": 10,
                        "partial_score": 8,
                        "partial_score_2": 5
                             },
                    "items": [
                    
                        {
                            "item_id": 0,
                            "item_type": "question",
                            "item_icon": "",
                            
                                "data": {
                                        "component_name": "question",
                                        "component_id": "LIVZCJRVRCC7EVEBWJPTVYKZRA4",
                                        "file_name": [ "question", "question_7H42UVS3MALULLR23NS63FN25Q"]
                                    }
                                     
                        } 
                            ]
                     } ,
                    {
                     "id":"L5ZOVPJKFTRLUPB4CELSEGYA66Q",
                    "level_id": 1,
                    "level_name": "Medium",
                    "scoring_system": {
                        "max_score": 10,
                        "partial_score": 8,
                        "partial_score_2": 5
                             },
                    "items": [
                    
                        {
                            "item_id": 0,
                            "item_type": "question",
                            "item_icon": "",
                            
                                "data": {
                                        "component_name": "question",
                                        "component_id": "LIUMJL3QUUM5EZG5VJNHPWZXDEU",
                                        "file_name": [ "question", "question_7H42UVS3MALULLR23NS63FN25Q"]
                                    }
                                     
                        } 
                            ]
                     } ,
                    {
                     "id":"L3WUHPDCW5PDEBA5NWS4QIF5HLM",
                    "level_id": 2,
                    "level_name": "Hard",
                    "scoring_system": {
                        "max_score": 10,
                        "partial_score": 8,
                        "partial_score_2": 5
                             },
                    "items": [
                    
                        {
                            "item_id": 0,
                            "item_type": "question",
                            "item_icon": "",
                            
                                "data": {
                                        "component_name": "question",
                                        "component_id": "LAV77TCKMINOERHO3FYOGIXOSHQ",
                                        "file_name": [ "question", "question_7H42UVS3MALULLR23NS63FN25Q"]
                                    }
                                     
                        } 
                            ]
                     } 
              ]
                 
                  }
                
    }
 }

    